README.rst
pelican_slug.py
setup.py
pelican_slug.egg-info/PKG-INFO
pelican_slug.egg-info/SOURCES.txt
pelican_slug.egg-info/dependency_links.txt
pelican_slug.egg-info/requires.txt
pelican_slug.egg-info/top_level.txt