Metadata-Version: 1.1
Name: pelican-slug
Version: 0.1
Summary: Pelican plugin to make a multi-byte slug the alphabetical one.
Home-page: https://github.com/wutali/pelican_slug
Author: Takahiro Fujiwara
Author-email: email@wuta.li
License: UNKNOWN
Download-URL: https://github.com/wutali/pelican_slug/tarball/master
Platform: UNKNOWN
